pyutss/__init__.py
pyutss/analysis/__init__.py
pyutss/analysis/monte_carlo.py
pyutss/data/__init__.py
pyutss/data/config.py
pyutss/data/models.py
pyutss/data/sources.py
pyutss/data/providers/__init__.py
pyutss/data/providers/base.py
pyutss/data/providers/jquants.py
pyutss/data/providers/registry.py
pyutss/data/providers/yahoo.py
pyutss/engine/__init__.py
pyutss/engine/backtest.py
pyutss/engine/evaluator.py
pyutss/engine/expr_parser.py
pyutss/engine/indicators.py
pyutss/metrics/__init__.py
pyutss/metrics/benchmark.py
pyutss/metrics/calculator.py
pyutss/optimization/__init__.py
pyutss/optimization/grid_search.py
pyutss/optimization/result.py
pyutss/optimization/splits.py
pyutss/optimization/walkforward.py
pyutss/portfolio/__init__.py
pyutss/portfolio/backtester.py
pyutss/portfolio/rebalancer.py
pyutss/portfolio/result.py
pyutss/portfolio/weights.py
pyutss/results/__init__.py
pyutss/results/plotting.py
pyutss/results/types.py
pyutss/visualization/__init__.py
pyutss/visualization/charts.py
pyutss/visualization/html.py
pyutss/visualization/tearsheet.py
pyutss-0.1.0.dist-info/METADATA
pyutss-0.1.0.dist-info/WHEEL
pyutss-0.1.0.dist-info/RECORD
